ppc/__init__.py
ppc/api.py
ppc/cli.py
ppc/file.py
ppc/sql.py
ppc-0.0.2.dist-info/LICENSE
ppc-0.0.2.dist-info/METADATA
ppc-0.0.2.dist-info/WHEEL
ppc-0.0.2.dist-info/entry_points.txt
ppc-0.0.2.dist-info/top_level.txt
ppc-0.0.2.dist-info/RECORD
