Metadata-Version: 2.1
Name: ppc
Version: 0.0.2
Summary: A Prisma Public Cloud API Client
Home-page: https://github.com/cloudcraeft/ppc
Author: cloudcraeft
Author-email: cloudcraeft@outlook.com
License: MIT License
Requires-Dist: requests
